spider_utils/__init__.py
spider_utils/client.py
spider_utils/download.py
spider_utils/spider.py
spider_utils/useragent.py
spider_utils/utils.py
spider_utils/data/mobile_user_agents.txt
spider_utils-2023.12.31.post2.dist-info/LICENSE
spider_utils-2023.12.31.post2.dist-info/METADATA
spider_utils-2023.12.31.post2.dist-info/WHEEL
spider_utils-2023.12.31.post2.dist-info/top_level.txt
spider_utils-2023.12.31.post2.dist-info/RECORD
